loan_approval_model/VERSION
loan_approval_model/__init__.py
loan_approval_model/config.yml
loan_approval_model/pipeline.py
loan_approval_model/predict.py
loan_approval_model/train_pipeline.py
loan_approval_model/config/__init__.py
loan_approval_model/config/core.py
loan_approval_model/datasets/test.csv
loan_approval_model/datasets/train.csv
loan_approval_model/processing/__init__.py
loan_approval_model/processing/data_manager.py
loan_approval_model/processing/validation.py
loan_approval_model/trained_model/naive_bayes_loan_model_v0.0.4.pkl
loan_approval_model-0.0.4.dist-info/METADATA
loan_approval_model-0.0.4.dist-info/WHEEL
loan_approval_model-0.0.4.dist-info/top_level.txt
loan_approval_model-0.0.4.dist-info/RECORD
