Metadata-Version: 2.4
Name: loan_approval_model
Version: 0.0.4
Summary: My package description
Author-email: Ekaterina Ashmanova <m2005713@edu.misis.ru>, Stepan Startsev <m2401133@edu.misis.ru>
License: MIT
Requires-Python: >=3.8
Requires-Dist: annotated-types==0.7.0
Requires-Dist: colorama==0.4.6
Requires-Dist: config==0.5.1
Requires-Dist: feature-engine==1.8.3
Requires-Dist: joblib==1.5.1
Requires-Dist: numpy==2.2.6
Requires-Dist: pandas==2.2.3
Requires-Dist: patsy==1.0.1
Requires-Dist: pydantic==2.11.5
Requires-Dist: pydantic-core==2.33.2
Requires-Dist: python-dateutil==2.9.0
Requires-Dist: pytz==2025.2
Requires-Dist: scikit-learn==1.6.1
Requires-Dist: scipy==1.15.3
Requires-Dist: statsmodels==0.14.4
Requires-Dist: strictyaml==1.7.3
Requires-Dist: typing-extensions==4.13.2
Provides-Extra: dev
Requires-Dist: pytest==8.3.5; extra == "dev"
Requires-Dist: iniconfig==2.1.0; extra == "dev"
Requires-Dist: pluggy==1.6.0; extra == "dev"
Requires-Dist: packaging==25.0; extra == "dev"
Requires-Dist: six==1.17.0; extra == "dev"
Requires-Dist: threadpoolctl==3.6.0; extra == "dev"
Requires-Dist: typing-inspection==0.4.1; extra == "dev"
Provides-Extra: test
Requires-Dist: pytest==8.3.5; extra == "test"
Requires-Dist: pytest-cov>=3.0.0; extra == "test"
Provides-Extra: docs
Requires-Dist: sphinx>=7.0.0; extra == "docs"
Requires-Dist: sphinx-rtd-theme>=1.3.0; extra == "docs"
Dynamic: requires-python
